__init__.py
traderman/__init__.py
traderman/connectors/__init__.py
traderman/connectors/binance.py
traderman/connectors/clients.py
traderman/forecasters/__init__.py
traderman/forecasters/benchmarks.py
traderman/forecasters/forecast.py
traderman/target/__init__.py
traderman/target/directional.py
traderman/target/explorations.py
traderman/tools/__init__.py
traderman/tools/data.py
traderman/tools/generic.py
traderman-0.0.1.dist-info/LICENSE
traderman-0.0.1.dist-info/METADATA
traderman-0.0.1.dist-info/WHEEL
traderman-0.0.1.dist-info/entry_points.txt
traderman-0.0.1.dist-info/top_level.txt
traderman-0.0.1.dist-info/RECORD
